[
  {
    "section": "conductor.proximity",
    "parameter": "pickup_radius_km",
    "value": "0.2",
    "value_type": "number",
    "default_value": "0.2",
    "constraints": {
      "min": 0.05,
      "max": 5.0,
      "step": 0.05,
      "unit": "kilometers"
    },
    "description": "Maximum distance from passenger for conductor to offer pickup",
    "display_name": "Pickup Radius",
    "ui_group": "Proximity Settings",
    "requires_restart": false
  },
  {
    "section": "conductor.proximity",
    "parameter": "boarding_time_window_minutes",
    "value": "5.0",
    "value_type": "number",
    "default_value": "5.0",
    "constraints": {
      "min": 1.0,
      "max": 30.0,
      "step": 0.5,
      "unit": "minutes"
    },
    "description": "Time window for passenger boarding eligibility",
    "display_name": "Boarding Time Window",
    "ui_group": "Proximity Settings",
    "requires_restart": false
  },
  {
    "section": "conductor.stop_duration",
    "parameter": "min_seconds",
    "value": "15.0",
    "value_type": "number",
    "default_value": "15.0",
    "constraints": {
      "min": 5.0,
      "max": 60.0,
      "step": 1.0,
      "unit": "seconds"
    },
    "description": "Minimum stop duration",
    "display_name": "Minimum Stop Duration",
    "ui_group": "Stop Duration",
    "requires_restart": false
  },
  {
    "section": "conductor.stop_duration",
    "parameter": "max_seconds",
    "value": "180.0",
    "value_type": "number",
    "default_value": "180.0",
    "constraints": {
      "min": 30.0,
      "max": 600.0,
      "step": 10.0,
      "unit": "seconds"
    },
    "description": "Maximum stop duration",
    "display_name": "Maximum Stop Duration",
    "ui_group": "Stop Duration",
    "requires_restart": false
  },
  {
    "section": "conductor.stop_duration",
    "parameter": "per_passenger_boarding_time",
    "value": "8.0",
    "value_type": "number",
    "default_value": "8.0",
    "constraints": {
      "min": 1.0,
      "max": 30.0,
      "step": 0.5,
      "unit": "seconds"
    },
    "description": "Time allocated per passenger for boarding",
    "display_name": "Boarding Time per Passenger",
    "ui_group": "Stop Duration",
    "requires_restart": false
  },
  {
    "section": "conductor.stop_duration",
    "parameter": "per_passenger_disembarking_time",
    "value": "5.0",
    "value_type": "number",
    "default_value": "5.0",
    "constraints": {
      "min": 1.0,
      "max": 20.0,
      "step": 0.5,
      "unit": "seconds"
    },
    "description": "Time allocated per passenger for disembarking",
    "display_name": "Disembarking Time per Passenger",
    "ui_group": "Stop Duration",
    "requires_restart": false
  },
  {
    "section": "conductor.operational",
    "parameter": "monitoring_interval_seconds",
    "value": "2.0",
    "value_type": "number",
    "default_value": "2.0",
    "constraints": {
      "min": 0.5,
      "max": 10.0,
      "step": 0.5,
      "unit": "seconds"
    },
    "description": "Interval for monitoring passenger status",
    "display_name": "Monitoring Interval",
    "ui_group": "Operational",
    "requires_restart": false
  },
  {
    "section": "conductor.operational",
    "parameter": "gps_precision_meters",
    "value": "10.0",
    "value_type": "number",
    "default_value": "10.0",
    "constraints": {
      "min": 1.0,
      "max": 100.0,
      "step": 1.0,
      "unit": "meters"
    },
    "description": "GPS precision for location tracking",
    "display_name": "GPS Precision",
    "ui_group": "Operational",
    "requires_restart": false
  },
  {
    "section": "driver.waypoints",
    "parameter": "proximity_threshold_km",
    "value": "0.05",
    "value_type": "number",
    "default_value": "0.05",
    "constraints": {
      "min": 0.01,
      "max": 0.5,
      "step": 0.01,
      "unit": "kilometers"
    },
    "description": "Distance threshold for waypoint arrival detection (50 meters default)",
    "display_name": "Waypoint Proximity Threshold",
    "ui_group": "Waypoints",
    "requires_restart": false
  },
  {
    "section": "driver.waypoints",
    "parameter": "broadcast_interval_seconds",
    "value": "5.0",
    "value_type": "number",
    "default_value": "5.0",
    "constraints": {
      "min": 1.0,
      "max": 30.0,
      "step": 1.0,
      "unit": "seconds"
    },
    "description": "Interval for broadcasting location updates",
    "display_name": "Location Broadcast Interval",
    "ui_group": "Waypoints",
    "requires_restart": false
  },
  {
    "section": "passenger_spawning.geographic",
    "parameter": "minimum_commute_distance_meters",
    "value": "200.0",
    "value_type": "number",
    "default_value": "200.0",
    "constraints": {
      "min": 50.0,
      "max": 5000.0,
      "step": 50.0,
      "unit": "meters"
    },
    "description": "Minimum distance passengers will travel by bus (distances below this are considered walking distance)",
    "display_name": "Minimum Commute Distance",
    "ui_group": "Geographic",
    "requires_restart": false
  },
  {
    "section": "passenger_spawning.geographic",
    "parameter": "spawn_radius_meters",
    "value": "500.0",
    "value_type": "number",
    "default_value": "500.0",
    "constraints": {
      "min": 50.0,
      "max": 5000.0,
      "step": 50.0,
      "unit": "meters"
    },
    "description": "Radius around spawn points for passenger placement",
    "display_name": "Spawn Radius",
    "ui_group": "Geographic",
    "requires_restart": false
  },
  {
    "section": "passenger_spawning.operational",
    "parameter": "continuous_mode",
    "value": "true",
    "value_type": "boolean",
    "default_value": "true",
    "constraints": {},
    "description": "Run spawning continuously in a loop (true) or execute once and exit (false)",
    "display_name": "Continuous Mode",
    "ui_group": "Operational",
    "requires_restart": true
  },
  {
    "section": "passenger_spawning.operational",
    "parameter": "spawn_interval_seconds",
    "value": "60",
    "value_type": "number",
    "default_value": "60",
    "constraints": {
      "min": 10,
      "max": 3600,
      "step": 5,
      "unit": "seconds"
    },
    "description": "Time interval between spawn cycles when running in continuous mode",
    "display_name": "Spawn Interval",
    "ui_group": "Operational",
    "requires_restart": false
  },
  {
    "section": "passenger_spawning.operational",
    "parameter": "enable_routespawner",
    "value": "true",
    "value_type": "boolean",
    "default_value": "true",
    "constraints": {},
    "description": "Enable route-based passenger spawning along transit routes",
    "display_name": "Enable Route Spawner",
    "ui_group": "Operational",
    "requires_restart": true
  },
  {
    "section": "passenger_spawning.operational",
    "parameter": "enable_depotspawner",
    "value": "true",
    "value_type": "boolean",
    "default_value": "true",
    "constraints": {},
    "description": "Enable depot-based passenger spawning at depot locations",
    "display_name": "Enable Depot Spawner",
    "ui_group": "Operational",
    "requires_restart": true
  },
  {
    "section": "vehicle_simulator.simulation",
    "parameter": "tick_time",
    "value": "1.0",
    "value_type": "number",
    "default_value": "1.0",
    "constraints": {
      "min": 0.1,
      "max": 10.0,
      "step": 0.1,
      "unit": "seconds"
    },
    "description": "Simulation tick rate (how often simulation updates)",
    "display_name": "Simulation Tick Time",
    "ui_group": "Simulation",
    "requires_restart": false
  },
  {
    "section": "vehicle_simulator.simulation",
    "parameter": "default_speed",
    "value": "60.0",
    "value_type": "number",
    "default_value": "60.0",
    "constraints": {
      "min": 10.0,
      "max": 150.0,
      "step": 5.0,
      "unit": "km/h"
    },
    "description": "Default vehicle speed when no route speed limit specified",
    "display_name": "Default Vehicle Speed",
    "ui_group": "Simulation",
    "requires_restart": false
  },
  {
    "section": "vehicle_simulator.engine",
    "parameter": "speed_model",
    "value": "kinematic",
    "value_type": "string",
    "default_value": "kinematic",
    "constraints": {
      "enum": ["kinematic", "linear"]
    },
    "description": "Physics model for vehicle movement (kinematic: realistic physics, linear: simple interpolation)",
    "display_name": "Speed Model",
    "ui_group": "Engine Physics",
    "requires_restart": false
  },
  {
    "section": "vehicle_simulator.engine",
    "parameter": "accel_limit",
    "value": "3.0",
    "value_type": "number",
    "default_value": "3.0",
    "constraints": {
      "min": 0.5,
      "max": 10.0,
      "step": 0.1,
      "unit": "m/s²"
    },
    "description": "Maximum acceleration rate for vehicles",
    "display_name": "Acceleration Limit",
    "ui_group": "Engine Physics",
    "requires_restart": false
  },
  {
    "section": "vehicle_simulator.engine",
    "parameter": "decel_limit",
    "value": "4.0",
    "value_type": "number",
    "default_value": "4.0",
    "constraints": {
      "min": 0.5,
      "max": 15.0,
      "step": 0.1,
      "unit": "m/s²"
    },
    "description": "Maximum deceleration rate for vehicles (braking)",
    "display_name": "Deceleration Limit",
    "ui_group": "Engine Physics",
    "requires_restart": false
  },
  {
    "section": "vehicle_simulator.engine",
    "parameter": "corner_slowdown",
    "value": "1.0",
    "value_type": "number",
    "default_value": "1.0",
    "constraints": {
      "min": 0.1,
      "max": 5.0,
      "step": 0.1,
      "unit": "multiplier"
    },
    "description": "Speed reduction factor when navigating corners",
    "display_name": "Corner Slowdown Factor",
    "ui_group": "Engine Physics",
    "requires_restart": false
  },
  {
    "section": "vehicle_simulator.gps",
    "parameter": "transmission_interval",
    "value": "1.0",
    "value_type": "number",
    "default_value": "1.0",
    "constraints": {
      "min": 0.1,
      "max": 60.0,
      "step": 0.1,
      "unit": "seconds"
    },
    "description": "How often GPS telemetry is transmitted",
    "display_name": "GPS Transmission Interval",
    "ui_group": "GPS Settings",
    "requires_restart": false
  },
  {
    "section": "vehicle_simulator.gps",
    "parameter": "enable_transmission",
    "value": "true",
    "value_type": "boolean",
    "default_value": "true",
    "constraints": {},
    "description": "Enable/disable GPS telemetry transmission",
    "display_name": "Enable GPS Transmission",
    "ui_group": "GPS Settings",
    "requires_restart": false
  },
  {
    "section": "passenger_spawning.operational",
    "parameter": "spawn_interval_seconds",
    "value": "60",
    "value_type": "number",
    "default_value": "60",
    "constraints": {
      "min": 10,
      "max": 600,
      "step": 5,
      "unit": "seconds"
    },
    "description": "Time interval between passenger spawn cycles",
    "display_name": "Spawn Interval",
    "ui_group": "Spawning Settings",
    "requires_restart": false
  }
]